{"errors":[],"warnings":[],"namedChunkGroups":{"app":{"chunks":[6,1],"assets":["webpack-runtime-01c09aa9b849607045f9.js","webpack-runtime-01c09aa9b849607045f9.js.map","app-a485d89985c3d5bc6eb5.js","app-a485d89985c3d5bc6eb5.js.map"],"children":{},"childAssets":{}},"component---src-pages-404-js":{"chunks":[0,2],"assets":["0-c0c95129d790a02d1f72.js","0-c0c95129d790a02d1f72.js.map","component---src-pages-404-js.90c750e3e73d6bb56685.css","component---src-pages-404-js-8257d1151cbe205d745e.js","component---src-pages-404-js-8257d1151cbe205d745e.js.map"],"children":{},"childAssets":{}},"component---src-pages-index-js":{"chunks":[0,3],"assets":["0-c0c95129d790a02d1f72.js","0-c0c95129d790a02d1f72.js.map","component---src-pages-index-js.90c750e3e73d6bb56685.css","component---src-pages-index-js-b3a61c84a8d547e8ee30.js","component---src-pages-index-js-b3a61c84a8d547e8ee30.js.map"],"children":{},"childAssets":{}},"component---src-pages-kiss-js":{"chunks":[0,4],"assets":["0-c0c95129d790a02d1f72.js","0-c0c95129d790a02d1f72.js.map","component---src-pages-kiss-js.90c750e3e73d6bb56685.css","component---src-pages-kiss-js-5a2a1ac1190cc2e62995.js","component---src-pages-kiss-js-5a2a1ac1190cc2e62995.js.map"],"children":{},"childAssets":{}}},"assetsByChunkName":{"app":["webpack-runtime-01c09aa9b849607045f9.js","app-a485d89985c3d5bc6eb5.js"],"component---src-pages-404-js":["0-c0c95129d790a02d1f72.js","component---src-pages-404-js.90c750e3e73d6bb56685.css","component---src-pages-404-js-8257d1151cbe205d745e.js"],"component---src-pages-index-js":["0-c0c95129d790a02d1f72.js","component---src-pages-index-js.90c750e3e73d6bb56685.css","component---src-pages-index-js-b3a61c84a8d547e8ee30.js"],"component---src-pages-kiss-js":["0-c0c95129d790a02d1f72.js","component---src-pages-kiss-js.90c750e3e73d6bb56685.css","component---src-pages-kiss-js-5a2a1ac1190cc2e62995.js"]}}